README.rst
setup.cfg
setup.py
dj_bitcoin.egg-info/PKG-INFO
dj_bitcoin.egg-info/SOURCES.txt
dj_bitcoin.egg-info/dependency_links.txt
dj_bitcoin.egg-info/not-zip-safe
dj_bitcoin.egg-info/top_level.txt
djbitcoin/__init__.py
djbitcoin/models.py
djbitcoin/serializers.py
djbitcoin/utils.py