Metadata-Version: 1.1
Name: dj-bitcoin
Version: 0.0.4
Summary: Django helpers for working with bitcoin
Home-page: https://github.com/silverlogic/dj-bitcoin
Author: Ryan Pineo
Author-email: ryanpineo@gmail.com
License: MIT
Platform: UNKNOWN
Classifier: Environment :: Web Environment
Classifier: Framework :: Django
Classifier: Intended Audience :: Developers
Classifier: License :: OSI Approved :: MIT License
Classifier: Operating System :: OS Independent
Classifier: Programming Language :: Python
Classifier: Programming Language :: Python :: 3
Classifier: Programming Language :: Python :: 3.4
Classifier: Programming Language :: Python :: 3.5
Classifier: Topic :: Internet :: WWW/HTTP
